{
"type": "FeatureCollection",
"name": "healthcare",
"crs": { "type": "name", "properties": { "name": "urn:ogc:def:crs:OGC:1.3:CRS84" } },
"features": [
{ "type": "Feature", "properties": { "element": "node", "id": 3950476354, "addr:housenumber": "146", "amenity": "pharmacy", "healthcare": "pharmacy", "name": "Pharmacie du Rond-Point", "phone": "21302709-94012403" }, "geometry": { "type": "Point", "coordinates": [ 2.4136825, 6.3625655 ] } },
{ "type": "Feature", "properties": { "element": "node", "id": 6966704885, "addr:housenumber": null, "amenity": "pharmacy", "healthcare": "pharmacy", "name": "Phamarcie Ste Foi", "phone": null }, "geometry": { "type": "Point", "coordinates": [ 2.4032719, 6.3686477 ] } },
{ "type": "Feature", "properties": { "element": "node", "id": 12061596155, "addr:housenumber": null, "amenity": "pharmacy", "healthcare": "pharmacy", "name": "Pharmacie de Gbegamey", "phone": null }, "geometry": { "type": "Point", "coordinates": [ 2.4083193, 6.3636651 ] } }
]
}
